{
  "status": 1,
  "error": "",
  "data": {
    "timestamp": 1542981576,
    "info": [{
      "pay_type_320": 0,
      "m4afilesize": 0,
      "price_sq": 0,
      "filesize": 3922862,
      "bitrate": 128,
      "trans_param": {
        "roaming_astrict": 0,
        "pay_block_tpl": 1,
        "musicpack_advance": 0,
        "display_rate": 0,
        "display": 0,
        "cid": -1
      },
      "price": 0,
      "inlist": 1,
      "old_cpy": 1,
      "pkg_price_sq": 0,
      "pay_type": 0,
      "topic_url": "",
      "fail_process_320": 0,
      "pkg_price": 0,
      "feetype": 0,
      "filename": "陈绮贞 - 旅行的意义",
      "price_320": 0,
      "extname": "mp3",
      "hash": "93A538E26D2345665E34A19BB0FFF08B",
      "mvhash": "D1EE0546B9B152743B90EBEC197B7CAE",
      "privilege": 0,
      "album_id": "982367",
      "sqprivilege": 0,
      "320privilege": 0,
      "album_audio_id": 32240927,
      "rp_type": "audio",
      "320filesize": 9692661,
      "rp_publish": 1,
      "has_accompany": 1,
      "topic_url_sq": "",
      "audio_id": 244643,
      "remark": "《渺渺》电影插曲",
      "pkg_price_320": 0,
      "fail_process": 0,
      "sqhash": "AE4278FCD08EB4A87DFF2FF49895CDFF",
      "duration": 244,
      "sqfilesize": 26148109,
      "pay_type_sq": 0,
      "fail_process_sq": 0,
      "brief": "",
      "topic_url_320": "",
      "320hash": "1B7981F93148EC2984AFEABC493AE045"
    }, {
      "pay_type_320": 3,
      "m4afilesize": 0,
      "price_sq": 200,
      "filesize": 3915022,
      "bitrate": 128,
      "trans_param": {
        "roaming_astrict": 0,
        "pay_block_tpl": 1,
        "musicpack_advance": 0,
        "display_rate": 0,
        "display": 0,
        "cid": 5512797
      },
      "price": 200,
      "inlist": 1,
      "old_cpy": 0,
      "pkg_price_sq": 1,
      "pay_type": 3,
      "topic_url": "",
      "fail_process_320": 4,
      "pkg_price": 1,
      "feetype": 0,
      "filename": "苏打绿 - 各站停靠",
      "price_320": 200,
      "extname": "mp3",
      "hash": "26B5B0F96D320B09298C46E685DF4623",
      "mvhash": "C453CCFD1CE51E3D85DF8DB1FA44328F",
      "privilege": 8,
      "album_id": "500289",
      "sqprivilege": 10,
      "320privilege": 10,
      "album_audio_id": 40291625,
      "rp_type": "audio",
      "320filesize": 9781633,
      "rp_publish": 1,
      "has_accompany": 1,
      "topic_url_sq": "",
      "audio_id": 65951,
      "remark": "春·日光",
      "pkg_price_320": 1,
      "fail_process": 4,
      "sqhash": "6C8E5E7B92149C505F120F13057D01C7",
      "duration": 245,
      "sqfilesize": 23504168,
      "pay_type_sq": 3,
      "fail_process_sq": 4,
      "brief": "",
      "topic_url_320": "",
      "320hash": "EA7E939DD39633AAD6A11D014FFB206E"
    }, {
      "pay_type_320": 3,
      "m4afilesize": 0,
      "price_sq": 200,
      "filesize": 3105981,
      "bitrate": 128,
      "trans_param": {
        "roaming_astrict": 0,
        "pay_block_tpl": 1,
        "musicpack_advance": 0,
        "display_rate": 0,
        "display": 0,
        "cid": 3837895
      },
      "price": 200,
      "inlist": 1,
      "old_cpy": 0,
      "pkg_price_sq": 1,
      "pay_type": 3,
      "topic_url": "",
      "fail_process_320": 4,
      "pkg_price": 1,
      "feetype": 0,
      "filename": "苏打绿 - 游乐",
      "price_320": 200,
      "extname": "mp3",
      "hash": "11E8FCAFF741A613386B762F24715E25",
      "mvhash": "5E9C437C20AFBB6DAC87C88EEB95A422",
      "privilege": 8,
      "album_id": "974765",
      "sqprivilege": 10,
      "320privilege": 10,
      "album_audio_id": 32170852,
      "rp_type": "audio",
      "320filesize": 7758312,
      "rp_publish": 1,
      "has_accompany": 1,
      "topic_url_sq": "",
      "audio_id": 78509,
      "remark": "无与伦比的美丽",
      "pkg_price_320": 1,
      "fail_process": 4,
      "sqhash": "FF5E13E8791B9CE7D52DCD312F952BDE",
      "duration": 194,
      "sqfilesize": 23415660,
      "pay_type_sq": 3,
      "fail_process_sq": 4,
      "brief": "",
      "topic_url_320": "",
      "320hash": "F8D6EC40E2070B348317C3060A56E37C"
    }, {
      "pay_type_320": 3,
      "m4afilesize": 0,
      "price_sq": 200,
      "filesize": 4583060,
      "bitrate": 128,
      "trans_param": {
        "roaming_astrict": 0,
        "pay_block_tpl": 1,
        "musicpack_advance": 0,
        "display_rate": 0,
        "display": 0,
        "cid": 4950111
      },
      "price": 200,
      "inlist": 1,
      "old_cpy": 0,
      "pkg_price_sq": 1,
      "pay_type": 3,
      "topic_url": "",
      "fail_process_320": 4,
      "pkg_price": 1,
      "feetype": 0,
      "filename": "杨丞琳 - 带我走",
      "price_320": 200,
      "extname": "mp3",
      "hash": "19225C81C2F5A926B1DECEB65854F833",
      "mvhash": "3A8E3C071AE03DACBD817F4BD13DCDDB",
      "privilege": 8,
      "album_id": "555831",
      "sqprivilege": 10,
      "320privilege": 10,
      "album_audio_id": 28117787,
      "rp_type": "audio",
      "320filesize": 11641335,
      "rp_publish": 1,
      "has_accompany": 1,
      "topic_url_sq": "",
      "audio_id": 3406655,
      "remark": "《不良笑花》电视剧片尾曲",
      "pkg_price_320": 1,
      "fail_process": 4,
      "sqhash": "0002785B5AA713E0D666D5E4F38D0F15",
      "duration": 286,
      "sqfilesize": 30809913,
      "pay_type_sq": 3,
      "fail_process_sq": 4,
      "brief": "",
      "topic_url_320": "",
      "320hash": "9BE74646AE34D40A2EEDF0B8D9974C7F"
    }, {
      "pay_type_320": 3,
      "m4afilesize": 0,
      "price_sq": 200,
      "filesize": 3831894,
      "bitrate": 128,
      "trans_param": {
        "roaming_astrict": 0,
        "pay_block_tpl": 1,
        "musicpack_advance": 0,
        "display_rate": 0,
        "display": 0,
        "cid": 2556312
      },
      "price": 200,
      "inlist": 1,
      "old_cpy": 0,
      "pkg_price_sq": 1,
      "pay_type": 3,
      "topic_url": "",
      "fail_process_320": 4,
      "pkg_price": 1,
      "feetype": 0,
      "filename": "周杰伦 - 米兰的小铁匠",
      "price_320": 200,
      "extname": "mp3",
      "hash": "FBFB90E741492E0756A1B5D61BE82433",
      "mvhash": "144F545367D597118C3902777B5B7E12",
      "privilege": 8,
      "album_id": "961807",
      "sqprivilege": 10,
      "320privilege": 10,
      "album_audio_id": 32055667,
      "rp_type": "audio",
      "320filesize": 9625850,
      "rp_publish": 1,
      "has_accompany": 1,
      "topic_url_sq": "",
      "audio_id": 188727,
      "remark": "八度空间",
      "pkg_price_320": 1,
      "fail_process": 4,
      "sqhash": "6B0A73B5C0E22E83E2818CE524E23314",
      "duration": 238,
      "sqfilesize": 25393115,
      "pay_type_sq": 3,
      "fail_process_sq": 4,
      "brief": "",
      "topic_url_320": "",
      "320hash": "FD91BF6CDDD4835B316D134D8B5D5A3F"
    }, {
      "pay_type_320": 3,
      "m4afilesize": 0,
      "price_sq": 200,
      "filesize": 3346599,
      "bitrate": 128,
      "trans_param": {
        "roaming_astrict": 0,
        "pay_block_tpl": 1,
        "musicpack_advance": 0,
        "display_rate": 0,
        "display": 0,
        "cid": 2556287
      },
      "price": 200,
      "inlist": 1,
      "old_cpy": 0,
      "pkg_price_sq": 1,
      "pay_type": 3,
      "topic_url": "",
      "fail_process_320": 4,
      "pkg_price": 1,
      "feetype": 0,
      "filename": "周杰伦 - 伊斯坦堡",
      "price_320": 200,
      "extname": "mp3",
      "hash": "EA80EEBAF1CA2E20D524471452A4BADA",
      "mvhash": "8919CBE5B7C18BE9A21E67EC59C5987B",
      "privilege": 8,
      "album_id": "978031",
      "sqprivilege": 10,
      "320privilege": 10,
      "album_audio_id": 64531902,
      "rp_type": "audio",
      "320filesize": 8268463,
      "rp_publish": 1,
      "has_accompany": 1,
      "topic_url_sq": "",
      "audio_id": 25158,
      "remark": "Jay",
      "pkg_price_320": 1,
      "fail_process": 4,
      "sqhash": "60AD9CF9CD344F49AB2E5C709235EBDD",
      "duration": 209,
      "sqfilesize": 22448488,
      "pay_type_sq": 3,
      "fail_process_sq": 4,
      "brief": "",
      "topic_url_320": "",
      "320hash": "548762165CD729B3B73107919566F529"
    }, {
      "pay_type_320": 3,
      "m4afilesize": 0,
      "price_sq": 200,
      "filesize": 3357035,
      "bitrate": 128,
      "trans_param": {
        "roaming_astrict": 0,
        "pay_block_tpl": 1,
        "musicpack_advance": 0,
        "display_rate": 0,
        "display": 0,
        "cid": 5107307
      },
      "price": 200,
      "inlist": 1,
      "old_cpy": 1,
      "pkg_price_sq": 1,
      "pay_type": 3,
      "topic_url": "",
      "fail_process_320": 4,
      "pkg_price": 1,
      "feetype": 0,
      "filename": "孙燕姿 - 遇见",
      "price_320": 200,
      "extname": "mp3",
      "hash": "AF8714B2944BA1A0D6745BBE931E8C22",
      "mvhash": "7D0B68DC456B65853D2BF70B7FF743BE",
      "privilege": 8,
      "album_id": "885882",
      "sqprivilege": 10,
      "320privilege": 10,
      "album_audio_id": 31303273,
      "rp_type": "audio",
      "320filesize": 8444922,
      "rp_publish": 1,
      "has_accompany": 1,
      "topic_url_sq": "",
      "audio_id": 335039,
      "remark": "《向左走，向右走》电影主题曲",
      "pkg_price_320": 1,
      "fail_process": 4,
      "sqhash": "E4C04123623F66C41667C1D4F6940D97",
      "duration": 209,
      "sqfilesize": 20365969,
      "pay_type_sq": 3,
      "fail_process_sq": 4,
      "brief": "",
      "topic_url_320": "",
      "320hash": "77C7913D3BE4E00EC702DB84535787E9"
    }, {
      "pay_type_320": 3,
      "m4afilesize": 0,
      "price_sq": 200,
      "filesize": 4495237,
      "bitrate": 128,
      "trans_param": {
        "roaming_astrict": 0,
        "pay_block_tpl": 1,
        "musicpack_advance": 0,
        "display_rate": 0,
        "display": 0,
        "cid": 5110555
      },
      "price": 200,
      "inlist": 1,
      "old_cpy": 0,
      "pkg_price_sq": 1,
      "pay_type": 3,
      "topic_url": "",
      "fail_process_320": 4,
      "pkg_price": 1,
      "feetype": 0,
      "filename": "陶喆 - 飞机场的10:30",
      "price_320": 200,
      "extname": "mp3",
      "hash": "97518069719B86E9B5298DD7C6A41606",
      "mvhash": "8359148A77FF9252BCBF8B0A62CE75A4",
      "privilege": 8,
      "album_id": "972835",
      "sqprivilege": 10,
      "320privilege": 10,
      "album_audio_id": 32153874,
      "rp_type": "audio",
      "320filesize": 11226313,
      "rp_publish": 1,
      "has_accompany": 1,
      "topic_url_sq": "",
      "audio_id": 2542129,
      "remark": "David Tao 同名专辑",
      "pkg_price_320": 1,
      "fail_process": 4,
      "sqhash": "31FFE958BB3399FE51A201838EBE49A8",
      "duration": 280,
      "sqfilesize": 31369955,
      "pay_type_sq": 3,
      "fail_process_sq": 4,
      "brief": "",
      "topic_url_320": "",
      "320hash": "18A020E57E09827E6F9C10802E03430B"
    }, {
      "pay_type_320": 3,
      "m4afilesize": 0,
      "price_sq": 200,
      "filesize": 3324282,
      "bitrate": 128,
      "trans_param": {
        "roaming_astrict": 0,
        "pay_block_tpl": 1,
        "musicpack_advance": 0,
        "display_rate": 0,
        "display": 0,
        "cid": 5507373
      },
      "price": 200,
      "inlist": 1,
      "old_cpy": 1,
      "pkg_price_sq": 1,
      "pay_type": 3,
      "topic_url": "",
      "fail_process_320": 4,
      "pkg_price": 1,
      "feetype": 0,
      "filename": "陈奕迅 - 岁月如歌",
      "price_320": 200,
      "extname": "mp3",
      "hash": "7CD61A6067A57ABECA1F629442820426",
      "mvhash": "3E982BA592F41E205DD2EA71EC64DB9C",
      "privilege": 8,
      "album_id": "1737784",
      "sqprivilege": 10,
      "320privilege": 10,
      "album_audio_id": 39561486,
      "rp_type": "audio",
      "320filesize": 8343509,
      "rp_publish": 1,
      "has_accompany": 1,
      "topic_url_sq": "",
      "audio_id": 160751,
      "remark": "《冲上云霄》电影主题曲",
      "pkg_price_320": 1,
      "fail_process": 4,
      "sqhash": "586B5658FE15261DC8E223048B15DB39",
      "duration": 207,
      "sqfilesize": 21363019,
      "pay_type_sq": 3,
      "fail_process_sq": 4,
      "brief": "",
      "topic_url_320": "",
      "320hash": "160AC40CA9443CEEE41D5C15AB7CBE51"
    }, {
      "pay_type_320": 3,
      "m4afilesize": 0,
      "price_sq": 200,
      "filesize": 3808025,
      "bitrate": 128,
      "trans_param": {
        "roaming_astrict": 0,
        "pay_block_tpl": 1,
        "musicpack_advance": 0,
        "display_rate": 0,
        "display": 0,
        "cid": 5114770
      },
      "price": 200,
      "inlist": 1,
      "old_cpy": 1,
      "pkg_price_sq": 1,
      "pay_type": 3,
      "topic_url": "",
      "fail_process_320": 4,
      "pkg_price": 1,
      "feetype": 0,
      "filename": "杨千嬅 - 自由行",
      "price_320": 200,
      "extname": "mp3",
      "hash": "4A65852ECC52A62A2E40642A7516BD0B",
      "mvhash": "EDAB093688E0BDE7D00564DEFDA8CA27",
      "privilege": 8,
      "album_id": "521033",
      "sqprivilege": 10,
      "320privilege": 10,
      "album_audio_id": 27524577,
      "rp_type": "audio",
      "320filesize": 9316437,
      "rp_publish": 1,
      "has_accompany": 1,
      "topic_url_sq": "",
      "audio_id": 85050,
      "remark": "金牌10年精选系列",
      "pkg_price_320": 1,
      "fail_process": 4,
      "sqhash": "92EB113F38E3C59F91F1026F98BD8D24",
      "duration": 238,
      "sqfilesize": 26211341,
      "pay_type_sq": 3,
      "fail_process_sq": 4,
      "brief": "",
      "topic_url_320": "",
      "320hash": "EE3C676B86B43DA2CCE00DADABEF3A12"
    }, {
      "pay_type_320": 3,
      "m4afilesize": 0,
      "price_sq": 200,
      "filesize": 3605860,
      "bitrate": 128,
      "trans_param": {
        "roaming_astrict": 0,
        "pay_block_tpl": 1,
        "musicpack_advance": 0,
        "display_rate": 0,
        "display": 0,
        "cid": 5113378
      },
      "price": 200,
      "inlist": 1,
      "old_cpy": 1,
      "pkg_price_sq": 1,
      "pay_type": 3,
      "topic_url": "",
      "fail_process_320": 4,
      "pkg_price": 1,
      "feetype": 0,
      "filename": "古巨基 - 罗马假期",
      "price_320": 200,
      "extname": "mp3",
      "hash": "B833E9CA44E8F6CC368F0C3E8997D0C1",
      "mvhash": "B24257874805BA5F1C9BB321380F69C6",
      "privilege": 8,
      "album_id": "500371",
      "sqprivilege": 10,
      "320privilege": 10,
      "album_audio_id": 27986397,
      "rp_type": "audio",
      "320filesize": 9105439,
      "rp_publish": 1,
      "has_accompany": 1,
      "topic_url_sq": "",
      "audio_id": 556881,
      "remark": "金牌精选",
      "pkg_price_320": 1,
      "fail_process": 4,
      "sqhash": "41314B4D4BF884E2855C8D18278D4CFF",
      "duration": 225,
      "sqfilesize": 23416920,
      "pay_type_sq": 3,
      "fail_process_sq": 4,
      "brief": "",
      "topic_url_320": "",
      "320hash": "45CC51DA501E4B99ECE05F4B5D289E4D"
    }, {
      "pay_type_320": 3,
      "m4afilesize": 0,
      "price_sq": 200,
      "filesize": 3532732,
      "bitrate": 128,
      "trans_param": {
        "roaming_astrict": 0,
        "pay_block_tpl": 1,
        "musicpack_advance": 0,
        "display_rate": 0,
        "display": 0,
        "cid": 5111489
      },
      "price": 200,
      "inlist": 1,
      "old_cpy": 1,
      "pkg_price_sq": 1,
      "pay_type": 3,
      "topic_url": "",
      "fail_process_320": 4,
      "pkg_price": 1,
      "feetype": 0,
      "filename": "林嘉欣 - 恋之风景",
      "price_320": 200,
      "extname": "mp3",
      "hash": "403C9FF280A6A6BB0CE49014C1EE10C4",
      "mvhash": "1DADE213473C795E2C442105BB11435A",
      "privilege": 8,
      "album_id": "962338",
      "sqprivilege": 10,
      "320privilege": 10,
      "album_audio_id": 32060339,
      "rp_type": "audio",
      "320filesize": 8826536,
      "rp_publish": 1,
      "has_accompany": 1,
      "topic_url_sq": "",
      "audio_id": 50778,
      "remark": "《恋之风景》电影主题曲",
      "pkg_price_320": 1,
      "fail_process": 4,
      "sqhash": "F57552F5A921799B6ABAEED649A31E25",
      "duration": 220,
      "sqfilesize": 25610325,
      "pay_type_sq": 3,
      "fail_process_sq": 4,
      "brief": "",
      "topic_url_320": "",
      "320hash": "F8199B93A0019BB639EBF2246564BF4E"
    }, {
      "pay_type_320": 3,
      "m4afilesize": 0,
      "price_sq": 200,
      "filesize": 3793388,
      "bitrate": 128,
      "trans_param": {
        "roaming_astrict": 0,
        "pay_block_tpl": 1,
        "musicpack_advance": 0,
        "display_rate": 0,
        "display": 0,
        "cid": 7476966
      },
      "price": 200,
      "inlist": 1,
      "old_cpy": 0,
      "pkg_price_sq": 1,
      "pay_type": 3,
      "topic_url": "",
      "fail_process_320": 4,
      "pkg_price": 1,
      "feetype": 0,
      "filename": "王菀之 - (巴黎没有)摩天轮",
      "price_320": 200,
      "extname": "mp3",
      "hash": "55F379E5FEBDF7C595F5622A06EEF421",
      "mvhash": "",
      "privilege": 8,
      "album_id": "976745",
      "sqprivilege": 10,
      "320privilege": 10,
      "album_audio_id": 32188455,
      "rp_type": "audio",
      "320filesize": 9458825,
      "rp_publish": 1,
      "has_accompany": 1,
      "topic_url_sq": "",
      "audio_id": 85307,
      "remark": "诗情·画意",
      "pkg_price_320": 1,
      "fail_process": 4,
      "sqhash": "14D0053D120BB878CFC9BBB10DBB38C2",
      "duration": 236,
      "sqfilesize": 23013644,
      "pay_type_sq": 3,
      "fail_process_sq": 4,
      "brief": "",
      "topic_url_320": "",
      "320hash": "A9621FA84E2950F5F4B0AB714B0DCBA6"
    }, {
      "pay_type_320": 3,
      "m4afilesize": 0,
      "price_sq": 0,
      "filesize": 3219469,
      "bitrate": 128,
      "trans_param": {
        "roaming_astrict": 0,
        "pay_block_tpl": 1,
        "musicpack_advance": 0,
        "display_rate": 0,
        "display": 0,
        "cid": 4949867
      },
      "price": 200,
      "inlist": 1,
      "old_cpy": 1,
      "pkg_price_sq": 0,
      "pay_type": 3,
      "topic_url": "",
      "fail_process_320": 4,
      "pkg_price": 1,
      "feetype": 0,
      "filename": "坏碑唇 - 雷克雅未克的情书",
      "price_320": 200,
      "extname": "mp3",
      "hash": "16852B0EDD84AD0D31490F10B6DA513A",
      "mvhash": "",
      "privilege": 8,
      "album_id": "629392",
      "sqprivilege": 0,
      "320privilege": 10,
      "album_audio_id": 28952067,
      "rp_type": "audio",
      "320filesize": 8014924,
      "rp_publish": 1,
      "has_accompany": 1,
      "topic_url_sq": "",
      "audio_id": 1844278,
      "remark": "雷克雅未克的情书",
      "pkg_price_320": 1,
      "fail_process": 4,
      "sqhash": "",
      "duration": 199,
      "sqfilesize": 0,
      "pay_type_sq": 0,
      "fail_process_sq": 0,
      "brief": "",
      "topic_url_320": "",
      "320hash": "FEA5DB55AF11EC6FA96B36C138D17657"
    }, {
      "pay_type_320": 3,
      "m4afilesize": 0,
      "price_sq": 200,
      "filesize": 3624786,
      "bitrate": 128,
      "trans_param": {
        "roaming_astrict": 0,
        "pay_block_tpl": 1,
        "musicpack_advance": 0,
        "display_rate": 0,
        "display": 0,
        "cid": 7343717
      },
      "price": 200,
      "inlist": 1,
      "old_cpy": 0,
      "pkg_price_sq": 1,
      "pay_type": 3,
      "topic_url": "",
      "fail_process_320": 4,
      "pkg_price": 1,
      "feetype": 0,
      "filename": "吴雨霏 - 吴哥窟",
      "price_320": 200,
      "extname": "mp3",
      "hash": "1171FC6792C3D9D92FDE8E2568F952DF",
      "mvhash": "C9792A3B059FA52BDBE61FA30ADDCDC3",
      "privilege": 8,
      "album_id": "964426",
      "sqprivilege": 10,
      "320privilege": 10,
      "album_audio_id": 32079260,
      "rp_type": "audio",
      "320filesize": 8998881,
      "rp_publish": 1,
      "has_accompany": 1,
      "topic_url_sq": "",
      "audio_id": 24115,
      "remark": "我本人",
      "pkg_price_320": 1,
      "fail_process": 4,
      "sqhash": "60A515837643C4C0AAEA866234BE8A08",
      "duration": 224,
      "sqfilesize": 23607566,
      "pay_type_sq": 3,
      "fail_process_sq": 4,
      "brief": "",
      "topic_url_320": "",
      "320hash": "FC6128BD9E189D72344CB9A977647D27"
    }, {
      "pay_type_320": 3,
      "m4afilesize": 0,
      "price_sq": 200,
      "filesize": 3562987,
      "bitrate": 127,
      "trans_param": {
        "roaming_astrict": 0,
        "pay_block_tpl": 1,
        "musicpack_advance": 0,
        "display_rate": 0,
        "display": 0,
        "cid": 13500529
      },
      "price": 200,
      "inlist": 1,
      "old_cpy": 0,
      "pkg_price_sq": 1,
      "pay_type": 3,
      "topic_url": "",
      "fail_process_320": 4,
      "pkg_price": 1,
      "feetype": 0,
      "filename": "谢安琪 - 跟我走这世界",
      "price_320": 200,
      "extname": "mp3",
      "hash": "C950FB4D5DDBE5155E560D017E498E1B",
      "mvhash": "",
      "privilege": 8,
      "album_id": "983314",
      "sqprivilege": 10,
      "320privilege": 10,
      "album_audio_id": 32249499,
      "rp_type": "audio",
      "320filesize": 8912357,
      "rp_publish": 1,
      "has_accompany": 1,
      "topic_url_sq": "",
      "audio_id": 398614,
      "remark": "The First Day",
      "pkg_price_320": 1,
      "fail_process": 4,
      "sqhash": "E60971014908CD1E98C419F87B96A3FB",
      "duration": 222,
      "sqfilesize": 25286870,
      "pay_type_sq": 3,
      "fail_process_sq": 4,
      "brief": "",
      "topic_url_320": "",
      "320hash": "38FE4B1B7CA9CD58BAFBA39D1FBD88EF"
    }, {
      "pay_type_320": 0,
      "m4afilesize": 0,
      "price_sq": 0,
      "filesize": 3940518,
      "bitrate": 128,
      "trans_param": {
        "roaming_astrict": 0,
        "pay_block_tpl": 1,
        "musicpack_advance": 0,
        "display_rate": 0,
        "display": 0,
        "cid": -1
      },
      "price": 0,
      "inlist": 1,
      "old_cpy": 1,
      "pkg_price_sq": 0,
      "pay_type": 0,
      "topic_url": "",
      "fail_process_320": 0,
      "pkg_price": 0,
      "feetype": 0,
      "filename": "Supper Moment - 飞",
      "price_320": 0,
      "extname": "mp3",
      "hash": "D80CB2AC5E7EE917284CF707776FBC67",
      "mvhash": "268BF16ACF989D3B2E7D8C8081A69872",
      "privilege": 0,
      "album_id": "977947",
      "sqprivilege": 0,
      "320privilege": 0,
      "album_audio_id": 32199678,
      "rp_type": "audio",
      "320filesize": 9802186,
      "rp_publish": 1,
      "has_accompany": 1,
      "topic_url_sq": "",
      "audio_id": 574562,
      "remark": "小伙子出城记",
      "pkg_price_320": 0,
      "fail_process": 0,
      "sqhash": "",
      "duration": 246,
      "sqfilesize": 0,
      "pay_type_sq": 0,
      "fail_process_sq": 0,
      "brief": "",
      "topic_url_320": "",
      "320hash": "56BC6A95E128A86A72FAE9BBFD27AB22"
    }, {
      "pay_type_320": 3,
      "m4afilesize": 0,
      "price_sq": 200,
      "filesize": 4486954,
      "bitrate": 128,
      "trans_param": {
        "roaming_astrict": 0,
        "pay_block_tpl": 1,
        "musicpack_advance": 0,
        "display_rate": 0,
        "display": 0,
        "cid": 5651298
      },
      "price": 200,
      "inlist": 1,
      "old_cpy": 1,
      "pkg_price_sq": 1,
      "pay_type": 3,
      "topic_url": "",
      "fail_process_320": 4,
      "pkg_price": 1,
      "feetype": 0,
      "filename": "林依晨 - 美好的旅行",
      "price_320": 200,
      "extname": "mp3",
      "hash": "0E99BD063BBCBD0DCCC21A9288799797",
      "mvhash": "B2C2A4061A60EE53E6B1BCDE95BB2D1B",
      "privilege": 8,
      "album_id": "958929",
      "sqprivilege": 10,
      "320privilege": 10,
      "album_audio_id": 32029624,
      "rp_type": "audio",
      "320filesize": 11229676,
      "rp_publish": 1,
      "has_accompany": 1,
      "topic_url_sq": "",
      "audio_id": 61540,
      "remark": "《街角的小王子》电影主题曲",
      "pkg_price_320": 1,
      "fail_process": 4,
      "sqhash": "4A0AAE735F798310382B99CBDAD528D7",
      "duration": 280,
      "sqfilesize": 29976678,
      "pay_type_sq": 3,
      "fail_process_sq": 4,
      "brief": "",
      "topic_url_320": "",
      "320hash": "F442F0B758202FC3375C7379EDE444B1"
    }, {
      "pay_type_320": 3,
      "m4afilesize": 0,
      "price_sq": 200,
      "filesize": 3846605,
      "bitrate": 128,
      "trans_param": {
        "roaming_astrict": 0,
        "pay_block_tpl": 1,
        "musicpack_advance": 0,
        "display_rate": 0,
        "display": 0,
        "cid": 22109111
      },
      "price": 200,
      "inlist": 1,
      "old_cpy": 1,
      "pkg_price_sq": 1,
      "pay_type": 3,
      "topic_url": "",
      "fail_process_320": 4,
      "pkg_price": 1,
      "feetype": 0,
      "filename": "梁汉文 - 瀛环搜奇",
      "price_320": 200,
      "extname": "mp3",
      "hash": "6A99214276C6BF0581878D4FCD903612",
      "mvhash": "",
      "privilege": 8,
      "album_id": "579463",
      "sqprivilege": 10,
      "320privilege": 10,
      "album_audio_id": 28413367,
      "rp_type": "audio",
      "320filesize": 9703049,
      "rp_publish": 1,
      "has_accompany": 0,
      "topic_url_sq": "",
      "audio_id": 551627,
      "remark": "PG家长指引",
      "pkg_price_320": 1,
      "fail_process": 4,
      "sqhash": "17F56938679B29941A2B48BD2BCCDC45",
      "duration": 240,
      "sqfilesize": 24010331,
      "pay_type_sq": 3,
      "fail_process_sq": 4,
      "brief": "",
      "topic_url_320": "",
      "320hash": "AC41847EC790A21CC385FBE2E59361C5"
    }],
    "total": 19
  },
  "errcode": 0
}